starify/__init__.py
starify/galaxy.py
starify-0.0.1b2.dist-info/LICENSE
starify-0.0.1b2.dist-info/METADATA
starify-0.0.1b2.dist-info/WHEEL
starify-0.0.1b2.dist-info/top_level.txt
starify-0.0.1b2.dist-info/RECORD
