Metadata-Version: 2.1
Name: starify
Version: 0.0.1b2
Summary: Starify: convert string to asterisks for confidentiality display
Home-page: https://github.com/patrickphat/starify
Author: Truong-Phat Nguyen
Author-email: me@patrickphat.com
License: UNKNOWN
Platform: UNKNOWN
Classifier: Programming Language :: Python :: 3
Classifier: License :: OSI Approved :: MIT License
Classifier: Operating System :: OS Independent
Requires-Python: >3.6
Provides-Extra: dev
Requires-Dist: pytest ; extra == 'dev'
Requires-Dist: coverage ; extra == 'dev'
